{
  "data": [
    {
      "hovertemplate": "scen=Ampol-1p5DS\u003cbr\u003eyear=%{x}\u003cbr\u003eGW=%{y}\u003cextra\u003e\u003c\u002fextra\u003e",
      "legendgroup": "",
      "marker": {
        "color": "rgb(158,158,158)",
        "symbol": "circle",
        "size": 0.001
      },
      "mode": "markers",
      "name": "",
      "orientation": "v",
      "showlegend": false,
      "x": {
        "dtype": "i4",
        "bdata": "6QcAAOoHAADrBwAA7AcAAO0HAADuBwAA7wcAAPAHAADxBwAA8gcAAPMHAAD4BwAA\u002fQcAAAIIAAA="
      },
      "xaxis": "x3",
      "y": {
        "dtype": "i1",
        "bdata": "AAAAAAAAAAAAAAAAAAA="
      },
      "yaxis": "y3",
      "type": "scatter",
      "line": {
        "width": 0.1,
        "color": "rgb(158,158,158)"
      },
      "opacity": 0
    },
    {
      "hovertemplate": "scen=Ampol-2p5DS\u003cbr\u003eyear=%{x}\u003cbr\u003eGW=%{y}\u003cextra\u003e\u003c\u002fextra\u003e",
      "legendgroup": "",
      "marker": {
        "color": "rgb(158,158,158)",
        "symbol": "circle",
        "size": 0.001
      },
      "mode": "markers",
      "name": "",
      "orientation": "v",
      "showlegend": false,
      "x": {
        "dtype": "i4",
        "bdata": "6QcAAOoHAADrBwAA7AcAAO0HAADuBwAA7wcAAPAHAADxBwAA8gcAAPMHAAD4BwAA\u002fQcAAAIIAAA="
      },
      "xaxis": "x4",
      "y": {
        "dtype": "i1",
        "bdata": "AAAAAAAAAAAAAAAAAAA="
      },
      "yaxis": "y4",
      "type": "scatter",
      "line": {
        "width": 0.1,
        "color": "rgb(158,158,158)"
      },
      "opacity": 0
    },
    {
      "hovertemplate": "scen=Ampol-House-View\u003cbr\u003eyear=%{x}\u003cbr\u003eGW=%{y}\u003cextra\u003e\u003c\u002fextra\u003e",
      "legendgroup": "",
      "marker": {
        "color": "rgb(158,158,158)",
        "symbol": "circle",
        "size": 0.001
      },
      "mode": "markers",
      "name": "",
      "orientation": "v",
      "showlegend": false,
      "x": {
        "dtype": "i4",
        "bdata": "6QcAAOoHAADrBwAA7AcAAO0HAADuBwAA7wcAAPAHAADxBwAA8gcAAPMHAAD4BwAA\u002fQcAAAIIAAA="
      },
      "xaxis": "x",
      "y": {
        "dtype": "i1",
        "bdata": "AAAAAAAAAAAAAAAAAAA="
      },
      "yaxis": "y",
      "type": "scatter",
      "line": {
        "width": 0.1,
        "color": "rgb(158,158,158)"
      },
      "opacity": 0
    },
    {
      "fill": "tonexty",
      "name": "Wind",
      "showlegend": true,
      "stackgroup": "positive",
      "x": {
        "dtype": "i4",
        "bdata": "AggAAP0HAAD4BwAA8wcAAPIHAADxBwAA8AcAAO8HAADuBwAA7QcAAOwHAADrBwAA6gcAAOkHAAA="
      },
      "y": {
        "dtype": "f8",
        "bdata": "nV4IJ3pGe0AhQLpEwbt6QFu29qCV43lAlzU4rHIyeUCHrLmIp7F4QJVZ4eJ8YnhAyXplGHsSeEDIrrWF9Ll3QIlIWHEScXdAyib0ev8sd0DKJvR6\u002f+x2QKdAz4SnD0tA981m87nSSkDg4RliVJs4QA=="
      },
      "type": "scatter",
      "xaxis": "x3",
      "yaxis": "y3",
      "line": {
        "width": 0.1,
        "color": "rgb(120,190,32)"
      },
      "legendgroup": "Wind",
      "marker": {
        "color": "rgb(120,190,32)"
      },
      "fillcolor": "rgb(120,190,32)"
    },
    {
      "fill": "tonexty",
      "name": "Solar - Utility Solar",
      "showlegend": true,
      "stackgroup": "positive",
      "x": {
        "dtype": "i4",
        "bdata": "AggAAP0HAAD4BwAA8wcAAPIHAADxBwAA8AcAAO8HAADuBwAA7QcAAOwHAADrBwAA6gcAAOkHAAA="
      },
      "y": {
        "dtype": "f8",
        "bdata": "vbYnw6WyYUDOyzjNCFZcQJNLJJD2U1tAzpeckY7WWUB63n8cRdZZQHEBgNIp1llAmPRNXxPWWUBPIrYv0NBYQGCjckDLkFZA+cgrJsZQVECl917b4E5TQJvexaqY2S9Am97FqpjZL0AcxIeX5gwlQA=="
      },
      "type": "scatter",
      "xaxis": "x3",
      "yaxis": "y3",
      "line": {
        "width": 0.1,
        "color": "rgb(232,119,34)"
      },
      "legendgroup": "Solar - Utility Solar",
      "marker": {
        "color": "rgb(232,119,34)"
      },
      "fillcolor": "rgb(232,119,34)"
    },
    {
      "fill": "tonexty",
      "name": "Solar - Rooftop Solar",
      "showlegend": true,
      "stackgroup": "positive",
      "x": {
        "dtype": "i4",
        "bdata": "AggAAP0HAAD4BwAA8wcAAPIHAADxBwAA8AcAAO8HAADuBwAA7QcAAOwHAADrBwAA6gcAAOkHAAA="
      },
      "y": {
        "dtype": "f8",
        "bdata": "Mwm2SLyPWkByl\u002f9CbgBWQNfQjcUZQ1FAiI2dVHYZSkDUIdTIWktJQIuHgKhtk0hATacFf\u002fHBR0AFMZy4jbJGQCUw5+KrTkVARH+3Q3qmQ0DRLgG73dpBQNf4TPbP4z5AL0ymCka1PECPxMvTuTI6QA=="
      },
      "type": "scatter",
      "xaxis": "x3",
      "yaxis": "y3",
      "line": {
        "width": 0.1,
        "color": "rgb(255,184,28)"
      },
      "legendgroup": "Solar - Rooftop Solar",
      "marker": {
        "color": "rgb(255,184,28)"
      },
      "fillcolor": "rgb(255,184,28)"
    },
    {
      "fill": "tonexty",
      "name": "Turbine - Open Cycle Gas Turbine (OCGT)",
      "showlegend": true,
      "stackgroup": "positive",
      "x": {
        "dtype": "i4",
        "bdata": "AggAAP0HAAD4BwAA8wcAAPIHAADxBwAA8AcAAO8HAADuBwAA7QcAAOwHAADrBwAA6gcAAOkHAAA="
      },
      "y": {
        "dtype": "f8",
        "bdata": "wIgN29qhAkB0jRH1mfoZQLejskrQyyBAeTTkj1i2IkApCYm0jX8jQHvBpzl50SNAQMBatWtCJEBAwFq1a0IkQCl4CrlSbyVAKXgKuVJvJUApeAq5Um8lQJ6Y9WIodyVAd2fttgtdJUDopPeNr40lQA=="
      },
      "type": "scatter",
      "xaxis": "x3",
      "yaxis": "y3",
      "line": {
        "width": 0.1,
        "color": "rgb(0,0,128)"
      },
      "legendgroup": "Turbine - Open Cycle Gas Turbine (OCGT)",
      "marker": {
        "color": "rgb(0,0,128)"
      },
      "fillcolor": "rgb(0,0,128)"
    },
    {
      "fill": "tonexty",
      "name": "Turbine - Steam - Black Coal",
      "showlegend": true,
      "stackgroup": "positive",
      "x": {
        "dtype": "i4",
        "bdata": "AggAAP0HAAD4BwAA8wcAAPIHAADxBwAA8AcAAO8HAADuBwAA7QcAAOwHAADrBwAA6gcAAOkHAAA="
      },
      "y": {
        "dtype": "f8",
        "bdata": "BICJJaUktz79\u002fzuAdYTKPjmmWgjg\u002fnE\u002fqksyCsESoT\u002fK4xPDohyhPyTLT0mQQ+s\u002fe8DyNJlD6z+RPvYO\u002f7jyPx7gOQ4TJhtAhfrlbP67IkDe4rk9WXcpQLKd76fGmzFAsp3vp8abMUCyne+nxpsxQA=="
      },
      "type": "scatter",
      "xaxis": "x3",
      "yaxis": "y3",
      "line": {
        "width": 0.1,
        "color": "rgb(0,0,0)"
      },
      "legendgroup": "Turbine - Steam - Black Coal",
      "marker": {
        "color": "rgb(0,0,0)"
      },
      "fillcolor": "rgb(0,0,0)"
    },
    {
      "fill": "tonexty",
      "name": "Hydro Plant",
      "showlegend": true,
      "stackgroup": "positive",
      "x": {
        "dtype": "i4",
        "bdata": "AggAAP0HAAD4BwAA8wcAAPIHAADxBwAA8AcAAO8HAADuBwAA7QcAAOwHAADrBwAA6gcAAOkHAAA="
      },
      "y": {
        "dtype": "f8",
        "bdata": "LUMc6+L2HEAtQxzr4vYcQC1DHOvi9hxAidLe4AtTHUCJ0t7gC1MdQInS3uALUx1AidLe4AtTHUCJ0t7gC1MdQInS3uALUx1AidLe4AtTHUCJ0t7gC1MdQInS3uALUx1AidLe4AtTHUAzZdH1rKIcQA=="
      },
      "type": "scatter",
      "xaxis": "x3",
      "yaxis": "y3",
      "line": {
        "width": 0.1,
        "color": "rgb(30,34,170)"
      },
      "legendgroup": "Hydro Plant",
      "marker": {
        "color": "rgb(30,34,170)"
      },
      "fillcolor": "rgb(30,34,170)"
    },
    {
      "fill": "tonexty",
      "name": "Turbine - Open Cycle Gas Turbine (OCGT) - Hydrogen",
      "showlegend": true,
      "stackgroup": "positive",
      "x": {
        "dtype": "i4",
        "bdata": "AggAAP0HAAD4BwAA8wcAAPIHAADxBwAA8AcAAO8HAADuBwAA7QcAAOwHAADrBwAA6gcAAOkHAAA="
      },
      "y": {
        "dtype": "f8",
        "bdata": "hGdFIwGPEECEZ0UjAY8QQIRnRSMBjxBAhGdFIwGPEECEZ0UjAY8QQIRnRSMBjxBAhGdFIwGPEECEZ0UjAY8QQIRnRSMBjxBAhGdFIwGPEECEZ0UjAY8QQNWbVxPP6g1A1ZtXE8\u002fqDUBBUw3NhvEEQA=="
      },
      "type": "scatter",
      "xaxis": "x3",
      "yaxis": "y3",
      "line": {
        "width": 0.1,
        "color": "rgb(0,122,83)"
      },
      "legendgroup": "Turbine - Open Cycle Gas Turbine (OCGT) - Hydrogen",
      "marker": {
        "color": "rgb(0,122,83)"
      },
      "fillcolor": "rgb(0,122,83)"
    },
    {
      "fill": "tonexty",
      "name": "Turbine - Closed Cycle Gas Turbine (CCGT)",
      "showlegend": true,
      "stackgroup": "positive",
      "x": {
        "dtype": "i4",
        "bdata": "AggAAP0HAAD4BwAA8wcAAPIHAADxBwAA8AcAAO8HAADuBwAA7QcAAOwHAADrBwAA6gcAAOkHAAA="
      },
      "y": {
        "dtype": "f8",
        "bdata": "YG5XEt6U8j9BHLmnx4AGQMRZ5hLAxgpAwHyFz9y3D0D5ei5fwbcPQN1o9jq7tw9AD5wzorS3D0APnDOitLcPQA+cM6K0tw9AD5wzorS3D0Cti9toAO8PQK2L22gA7w9ArYvbaADvD0Cti9toAO8PQA=="
      },
      "type": "scatter",
      "xaxis": "x3",
      "yaxis": "y3",
      "line": {
        "width": 0.1,
        "color": "rgb(117,117,121)"
      },
      "legendgroup": "Turbine - Closed Cycle Gas Turbine (CCGT)",
      "marker": {
        "color": "rgb(117,117,121)"
      },
      "fillcolor": "rgb(117,117,121)"
    },
    {
      "fill": "tonexty",
      "name": "Turbine - Steam - Brown Coal",
      "showlegend": true,
      "stackgroup": "positive",
      "x": {
        "dtype": "i4",
        "bdata": "AggAAP0HAAD4BwAA8wcAAPIHAADxBwAA8AcAAO8HAADuBwAA7QcAAOwHAADrBwAA6gcAAOkHAAA="
      },
      "y": {
        "dtype": "f8",
        "bdata": "CIA0tB12nT4A4PzSycy4PvBvFPa20M0+\u002fWMjPt\u002fw4j4ARo2eCIf3PgP+3on4Wfs+APJhsP0iAD9rMySIgevxP7aur\u002fmB6\u002fE\u002fYIB5CYPr8T+gr3mvWI8EQEjhehSuRxNASOF6FK5HE0BI4XoUrkcTQA=="
      },
      "type": "scatter",
      "xaxis": "x3",
      "yaxis": "y3",
      "line": {
        "width": 0.1,
        "color": "rgb(102,51,0)"
      },
      "legendgroup": "Turbine - Steam - Brown Coal",
      "marker": {
        "color": "rgb(102,51,0)"
      },
      "fillcolor": "rgb(102,51,0)"
    },
    {
      "fill": "tonexty",
      "name": "Solar - Solar Thermal",
      "showlegend": true,
      "stackgroup": "positive",
      "x": {
        "dtype": "i4",
        "bdata": "AggAAP0HAAD4BwAA8wcAAPIHAAA="
      },
      "y": {
        "dtype": "f8",
        "bdata": "VfIgdOoqNEBlq5ll4w8nQKj4105\u002fvwFAFprqHb\u002fIVj+VXVg0Vm07Pw=="
      },
      "type": "scatter",
      "xaxis": "x3",
      "yaxis": "y3",
      "line": {
        "width": 0.1,
        "color": "rgb(107,142,35)"
      },
      "legendgroup": "Solar - Solar Thermal",
      "marker": {
        "color": "rgb(107,142,35)"
      },
      "fillcolor": "rgb(107,142,35)"
    },
    {
      "fill": "tonexty",
      "name": "Engine - Reciprocating Engine",
      "showlegend": true,
      "stackgroup": "positive",
      "x": {
        "dtype": "i4",
        "bdata": "AggAAP0HAAD4BwAA8wcAAPIHAADxBwAA8AcAAO8HAADuBwAA7QcAAOwHAADrBwAA6gcAAOkHAAA="
      },
      "y": {
        "dtype": "f8",
        "bdata": "DPv6NRTE2D9wg\u002fEOE7jpPwBuFi8Whu0\u002fAG4WLxaG7T8AbhYvFobtPwBuFi8Whu0\u002fAG4WLxaG7T8AbhYvFobtPwBuFi8Whu0\u002fAG4WLxaG7T8AbhYvFobtPwBuFi8Whu0\u002fiuWWVkPi7D+A\u002fuhV\u002fSDrPw=="
      },
      "type": "scatter",
      "xaxis": "x3",
      "yaxis": "y3",
      "line": {
        "width": 0.1,
        "color": "rgb(113,204,152)"
      },
      "legendgroup": "Engine - Reciprocating Engine",
      "marker": {
        "color": "rgb(113,204,152)"
      },
      "fillcolor": "rgb(113,204,152)"
    },
    {
      "fill": "tonexty",
      "name": "Engine - Cogeneration",
      "showlegend": true,
      "stackgroup": "positive",
      "x": {
        "dtype": "i4",
        "bdata": "AggAAP0HAAD4BwAA8wcAAPIHAADxBwAA8AcAAO8HAADuBwAA7QcAAOwHAADrBwAA6gcAAOkHAAA="
      },
      "y": {
        "dtype": "f8",
        "bdata": "I\u002fIHAsNRtD9AdPmn6s\u002fXP24Sg8DKoeE\u002fbhKDwMqh4T++nxov3STiP76fGi\u002fdJOI\u002fvp8aL90k4j++nxov3STiP5LLf0i\u002ffeM\u002fkst\u002fSL994z+Sy39Iv33jP5LLf0i\u002ffeM\u002fkst\u002fSL994z+Sy39Iv33jPw=="
      },
      "type": "scatter",
      "xaxis": "x3",
      "yaxis": "y3",
      "line": {
        "width": 0.1,
        "color": "rgb(67,194,204)"
      },
      "legendgroup": "Engine - Cogeneration",
      "marker": {
        "color": "rgb(67,194,204)"
      },
      "fillcolor": "rgb(67,194,204)"
    },
    {
      "fill": "tonexty",
      "name": "Turbine - Open Cycle Gas Turbine (OCGT) - Oil Distillate",
      "showlegend": true,
      "stackgroup": "positive",
      "x": {
        "dtype": "i4",
        "bdata": "8wcAAPIHAADxBwAA8AcAAO8HAADuBwAA7QcAAOwHAADrBwAA6gcAAOkHAAA="
      },
      "y": {
        "dtype": "f8",
        "bdata": "YJ9KrcY7kj+amZmZmZmpP1pkO99Pjd8\u002fWmQ730+N3z9aZDvfT43fP0w3iUFg5eQ\u002fTDeJQWDl5D9MN4lBYOXkP0w3iUFg5eQ\u002fTDeJQWDl5D9MN4lBYOXkPw=="
      },
      "type": "scatter",
      "xaxis": "x3",
      "yaxis": "y3",
      "line": {
        "width": 0.1,
        "color": "rgb(44,44,44)"
      },
      "legendgroup": "Turbine - Open Cycle Gas Turbine (OCGT) - Oil Distillate",
      "marker": {
        "color": "rgb(44,44,44)"
      },
      "fillcolor": "rgb(44,44,44)"
    },
    {
      "fill": "tonexty",
      "name": "Wind",
      "showlegend": false,
      "stackgroup": "positive",
      "x": {
        "dtype": "i4",
        "bdata": "AggAAP0HAAD4BwAA8wcAAPIHAADxBwAA8AcAAO8HAADuBwAA7QcAAOwHAADrBwAA6gcAAOkHAAA="
      },
      "y": {
        "dtype": "f8",
        "bdata": "sA2YPgiUeUCaQe\u002f85ip5QLTPqvBWsHhAFyiPApCNeECVP0PhOmB4QME9nIptOHhA7aBIT84BeECJLS+JJbJ3QPxve4pEaXdAdBjHyGEld0B0GMfIYeV2QPfNZvO50kpA981m87nSSkDg4RliVJs4QA=="
      },
      "type": "scatter",
      "xaxis": "x4",
      "yaxis": "y4",
      "line": {
        "width": 0.1,
        "color": "rgb(120,190,32)"
      },
      "legendgroup": "Wind",
      "marker": {
        "color": "rgb(120,190,32)"
      },
      "fillcolor": "rgb(120,190,32)"
    },
    {
      "fill": "tonexty",
      "name": "Solar - Utility Solar",
      "showlegend": false,
      "stackgroup": "positive",
      "x": {
        "dtype": "i4",
        "bdata": "AggAAP0HAAD4BwAA8wcAAPIHAADxBwAA8AcAAO8HAADuBwAA7QcAAOwHAADrBwAA6gcAAOkHAAA="
      },
      "y": {
        "dtype": "f8",
        "bdata": "lGwYtypfYUD44LhU\u002fQZhQNKwg5KTgmBAfghH73J+X0DuGOOngiFdQH81nRVLzlpAWnD2MK2EWEB6lQN6CEVWQLAS5FkhelVAIiW76LtJVEDNU+6d1kdTQJvexaqY2S9Am97FqpjZL0AcxIeX5gwlQA=="
      },
      "type": "scatter",
      "xaxis": "x4",
      "yaxis": "y4",
      "line": {
        "width": 0.1,
        "color": "rgb(232,119,34)"
      },
      "legendgroup": "Solar - Utility Solar",
      "marker": {
        "color": "rgb(232,119,34)"
      },
      "fillcolor": "rgb(232,119,34)"
    },
    {
      "fill": "tonexty",
      "name": "Solar - Rooftop Solar",
      "showlegend": false,
      "stackgroup": "positive",
      "x": {
        "dtype": "i4",
        "bdata": "AggAAP0HAAD4BwAA8wcAAPIHAADxBwAA8AcAAO8HAADuBwAA7QcAAOwHAADrBwAA6gcAAOkHAAA="
      },
      "y": {
        "dtype": "f8",
        "bdata": "IX0jyToLTkBO4S+9WfhIQGqgjplnQkZAGei2+dM\u002fREDTBCGrsOJDQMyKpF0Hf0NAuGsCnZUSQ0ArMV3QSKZCQFgY2NblJEJA2hiKKZB7QUBw4IRhMZpAQNf4TPbP4z5AL0ymCka1PECPxMvTuTI6QA=="
      },
      "type": "scatter",
      "xaxis": "x4",
      "yaxis": "y4",
      "line": {
        "width": 0.1,
        "color": "rgb(255,184,28)"
      },
      "legendgroup": "Solar - Rooftop Solar",
      "marker": {
        "color": "rgb(255,184,28)"
      },
      "fillcolor": "rgb(255,184,28)"
    },
    {
      "fill": "tonexty",
      "name": "Turbine - Open Cycle Gas Turbine (OCGT)",
      "showlegend": false,
      "stackgroup": "positive",
      "x": {
        "dtype": "i4",
        "bdata": "AggAAP0HAAD4BwAA8wcAAPIHAADxBwAA8AcAAO8HAADuBwAA7QcAAOwHAADrBwAA6gcAAOkHAAA="
      },
      "y": {
        "dtype": "f8",
        "bdata": "9V4MqtHKAUCO+JBcFY8ZQEVZcv4NliBABuqjQ5aAIkC2vkhoy0kjQAh3Z+22myNAzXUaaakMJEDNdRppqQwkQLYtymyQOSVAti3KbJA5JUC2LcpskDklQLJGPUSjSyVAd2fttgtdJUDopPeNr40lQA=="
      },
      "type": "scatter",
      "xaxis": "x4",
      "yaxis": "y4",
      "line": {
        "width": 0.1,
        "color": "rgb(0,0,128)"
      },
      "legendgroup": "Turbine - Open Cycle Gas Turbine (OCGT)",
      "marker": {
        "color": "rgb(0,0,128)"
      },
      "fillcolor": "rgb(0,0,128)"
    },
    {
      "fill": "tonexty",
      "name": "Turbine - Steam - Black Coal",
      "showlegend": false,
      "stackgroup": "positive",
      "x": {
        "dtype": "i4",
        "bdata": "AggAAP0HAAD4BwAA8wcAAPIHAADxBwAA8AcAAO8HAADuBwAA7QcAAOwHAADrBwAA6gcAAOkHAAA="
      },
      "y": {
        "dtype": "f8",
        "bdata": "\u002fw8dLdOL1j4IrGENaLT8PlF2at06fAVA9FZ\u002fdf58CUByXLaUoXAPQJ9hCE2D6xJAzLo6BXc9F0CBrdBTpRgaQJnmFM0mayBAXxbumGDMJUCvsVpg53EqQLKd76fGmzFAsp3vp8abMUCyne+nxpsxQA=="
      },
      "type": "scatter",
      "xaxis": "x4",
      "yaxis": "y4",
      "line": {
        "width": 0.1,
        "color": "rgb(0,0,0)"
      },
      "legendgroup": "Turbine - Steam - Black Coal",
      "marker": {
        "color": "rgb(0,0,0)"
      },
      "fillcolor": "rgb(0,0,0)"
    },
    {
      "fill": "tonexty",
      "name": "Hydro Plant",
      "showlegend": false,
      "stackgroup": "positive",
      "x": {
        "dtype": "i4",
        "bdata": "AggAAP0HAAD4BwAA8wcAAPIHAADxBwAA8AcAAO8HAADuBwAA7QcAAOwHAADrBwAA6gcAAOkHAAA="
      },
      "y": {
        "dtype": "f8",
        "bdata": "LUMc6+L2HEAtQxzr4vYcQC1DHOvi9hxAidLe4AtTHUCJ0t7gC1MdQInS3uALUx1AidLe4AtTHUCJ0t7gC1MdQInS3uALUx1AidLe4AtTHUCJ0t7gC1MdQInS3uALUx1AidLe4AtTHUAzZdH1rKIcQA=="
      },
      "type": "scatter",
      "xaxis": "x4",
      "yaxis": "y4",
      "line": {
        "width": 0.1,
        "color": "rgb(30,34,170)"
      },
      "legendgroup": "Hydro Plant",
      "marker": {
        "color": "rgb(30,34,170)"
      },
      "fillcolor": "rgb(30,34,170)"
    },
    {
      "fill": "tonexty",
      "name": "Turbine - Open Cycle Gas Turbine (OCGT) - Hydrogen",
      "showlegend": false,
      "stackgroup": "positive",
      "x": {
        "dtype": "i4",
        "bdata": "AggAAP0HAAD4BwAA8wcAAPIHAADxBwAA8AcAAO8HAADuBwAA7QcAAOwHAADrBwAA6gcAAOkHAAA="
      },
      "y": {
        "dtype": "f8",
        "bdata": "hGdFIwGPEECEZ0UjAY8QQIRnRSMBjxBAhGdFIwGPEECEZ0UjAY8QQIRnRSMBjxBAhGdFIwGPEECEZ0UjAY8QQIRnRSMBjxBAhGdFIwGPEECEZ0UjAY8QQNWbVxPP6g1A1ZtXE8\u002fqDUBBUw3NhvEEQA=="
      },
      "type": "scatter",
      "xaxis": "x4",
      "yaxis": "y4",
      "line": {
        "width": 0.1,
        "color": "rgb(0,122,83)"
      },
      "legendgroup": "Turbine - Open Cycle Gas Turbine (OCGT) - Hydrogen",
      "marker": {
        "color": "rgb(0,122,83)"
      },
      "fillcolor": "rgb(0,122,83)"
    },
    {
      "fill": "tonexty",
      "name": "Turbine - Closed Cycle Gas Turbine (CCGT)",
      "showlegend": false,
      "stackgroup": "positive",
      "x": {
        "dtype": "i4",
        "bdata": "AggAAP0HAAD4BwAA8wcAAPIHAADxBwAA8AcAAO8HAADuBwAA7QcAAOwHAADrBwAA6gcAAOkHAAA="
      },
      "y": {
        "dtype": "f8",
        "bdata": "F9eC\u002f5WU8j9V+2TgqIAGQAnzbSOoxgpAP5Z6L9C3D0DPYg6YurcPQA+cM6K0tw9AD5wzorS3D0APnDOitLcPQA+cM6K0tw9AD5wzorS3D0Cti9toAO8PQK2L22gA7w9ArYvbaADvD0Cti9toAO8PQA=="
      },
      "type": "scatter",
      "xaxis": "x4",
      "yaxis": "y4",
      "line": {
        "width": 0.1,
        "color": "rgb(117,117,121)"
      },
      "legendgroup": "Turbine - Closed Cycle Gas Turbine (CCGT)",
      "marker": {
        "color": "rgb(117,117,121)"
      },
      "fillcolor": "rgb(117,117,121)"
    },
    {
      "fill": "tonexty",
      "name": "Turbine - Steam - Brown Coal",
      "showlegend": false,
      "stackgroup": "positive",
      "x": {
        "dtype": "i4",
        "bdata": "AggAAP0HAAD4BwAA8wcAAPIHAADxBwAA8AcAAO8HAADuBwAA7QcAAOwHAADrBwAA6gcAAOkHAAA="
      },
      "y": {
        "dtype": "f8",
        "bdata": "6R+xiqOyuj4HMItaW6nYPohtGVZYj+I\u002fmrx6nHtk\u002fz8VrkfhehQLQBWuR+F6FAtAFa5H4XoUC0AVrkfhehQLQBWuR+F6FAtAFa5H4XoUC0AcIDZGqkcTQEjhehSuRxNASOF6FK5HE0BI4XoUrkcTQA=="
      },
      "type": "scatter",
      "xaxis": "x4",
      "yaxis": "y4",
      "line": {
        "width": 0.1,
        "color": "rgb(102,51,0)"
      },
      "legendgroup": "Turbine - Steam - Brown Coal",
      "marker": {
        "color": "rgb(102,51,0)"
      },
      "fillcolor": "rgb(102,51,0)"
    },
    {
      "fill": "tonexty",
      "name": "Solar - Solar Thermal",
      "showlegend": false,
      "stackgroup": "positive",
      "x": {
        "dtype": "i4",
        "bdata": "AggAAP0HAAD4BwAA8wcAAPIHAAA="
      },
      "y": {
        "dtype": "f8",
        "bdata": "5pXAsihp\u002fj8wVSpw4nv3P9c5qhKswGQ\u002f71yC0lzNUD8yzWiJ3zE3Pw=="
      },
      "type": "scatter",
      "xaxis": "x4",
      "yaxis": "y4",
      "line": {
        "width": 0.1,
        "color": "rgb(107,142,35)"
      },
      "legendgroup": "Solar - Solar Thermal",
      "marker": {
        "color": "rgb(107,142,35)"
      },
      "fillcolor": "rgb(107,142,35)"
    },
    {
      "fill": "tonexty",
      "name": "Engine - Reciprocating Engine",
      "showlegend": false,
      "stackgroup": "positive",
      "x": {
        "dtype": "i4",
        "bdata": "AggAAP0HAAD4BwAA8wcAAPIHAADxBwAA8AcAAO8HAADuBwAA7QcAAOwHAADrBwAA6gcAAOkHAAA="
      },
      "y": {
        "dtype": "f8",
        "bdata": "IOr7hG581z\u002f5+nE2QBTpP4rlllZD4uw\u002fiuWWVkPi7D+K5ZZWQ+LsP4rlllZD4uw\u002fiuWWVkPi7D+K5ZZWQ+LsP4rlllZD4uw\u002fiuWWVkPi7D+K5ZZWQ+LsP4rlllZD4uw\u002fiuWWVkPi7D+A\u002fuhV\u002fSDrPw=="
      },
      "type": "scatter",
      "xaxis": "x4",
      "yaxis": "y4",
      "line": {
        "width": 0.1,
        "color": "rgb(113,204,152)"
      },
      "legendgroup": "Engine - Reciprocating Engine",
      "marker": {
        "color": "rgb(113,204,152)"
      },
      "fillcolor": "rgb(113,204,152)"
    },
    {
      "fill": "tonexty",
      "name": "Engine - Cogeneration",
      "showlegend": false,
      "stackgroup": "positive",
      "x": {
        "dtype": "i4",
        "bdata": "AggAAP0HAAD4BwAA8wcAAPIHAADxBwAA8AcAAO8HAADuBwAA7QcAAOwHAADrBwAA6gcAAOkHAAA="
      },
      "y": {
        "dtype": "f8",
        "bdata": "I\u002fIHAsNRtD9AdPmn6s\u002fXP24Sg8DKoeE\u002fbhKDwMqh4T++nxov3STiP76fGi\u002fdJOI\u002fvp8aL90k4j++nxov3STiP5LLf0i\u002ffeM\u002fkst\u002fSL994z+Sy39Iv33jP5LLf0i\u002ffeM\u002fkst\u002fSL994z+Sy39Iv33jPw=="
      },
      "type": "scatter",
      "xaxis": "x4",
      "yaxis": "y4",
      "line": {
        "width": 0.1,
        "color": "rgb(67,194,204)"
      },
      "legendgroup": "Engine - Cogeneration",
      "marker": {
        "color": "rgb(67,194,204)"
      },
      "fillcolor": "rgb(67,194,204)"
    },
    {
      "fill": "tonexty",
      "name": "Turbine - Open Cycle Gas Turbine (OCGT) - Oil Distillate",
      "showlegend": false,
      "stackgroup": "positive",
      "x": {
        "dtype": "i4",
        "bdata": "8wcAAPIHAADxBwAA8AcAAO8HAADuBwAA7QcAAOwHAADrBwAA6gcAAOkHAAA="
      },
      "y": {
        "dtype": "f8",
        "bdata": "YJ9KrcY7kj+amZmZmZmpP1pkO99Pjd8\u002fWmQ730+N3z9aZDvfT43fP0w3iUFg5eQ\u002fTDeJQWDl5D9MN4lBYOXkP0w3iUFg5eQ\u002fTDeJQWDl5D9MN4lBYOXkPw=="
      },
      "type": "scatter",
      "xaxis": "x4",
      "yaxis": "y4",
      "line": {
        "width": 0.1,
        "color": "rgb(44,44,44)"
      },
      "legendgroup": "Turbine - Open Cycle Gas Turbine (OCGT) - Oil Distillate",
      "marker": {
        "color": "rgb(44,44,44)"
      },
      "fillcolor": "rgb(44,44,44)"
    },
    {
      "fill": "tonexty",
      "name": "Wind",
      "showlegend": false,
      "stackgroup": "positive",
      "x": {
        "dtype": "i4",
        "bdata": "AggAAP0HAAD4BwAA8wcAAPIHAADxBwAA8AcAAO8HAADuBwAA7QcAAOwHAADrBwAA6gcAAOkHAAA="
      },
      "y": {
        "dtype": "f8",
        "bdata": "g\u002fMa2inNeECoqy4NCJl4QMobAehMNnhAgHP3dLYPeED98Coz\u002fPt3QC36BGaW6ndA+M8WB5\u002fGd0DbypZg4KN3QAQ1JRNEaXdAdBjHyGEld0B0GMfIYeV2QPfNZvO50kpA981m87nSSkDg4RliVJs4QA=="
      },
      "type": "scatter",
      "xaxis": "x",
      "yaxis": "y",
      "line": {
        "width": 0.1,
        "color": "rgb(120,190,32)"
      },
      "legendgroup": "Wind",
      "marker": {
        "color": "rgb(120,190,32)"
      },
      "fillcolor": "rgb(120,190,32)"
    },
    {
      "fill": "tonexty",
      "name": "Solar - Utility Solar",
      "showlegend": false,
      "stackgroup": "positive",
      "x": {
        "dtype": "i4",
        "bdata": "AggAAP0HAAD4BwAA8wcAAPIHAADxBwAA8AcAAO8HAADuBwAA7QcAAOwHAADrBwAA6gcAAOkHAAA="
      },
      "y": {
        "dtype": "f8",
        "bdata": "pMnEkd3CVUDCZrjO165VQPPYG1p7C1VAJWAZAM1JVEBNh+THrElUQFp7G1CdSVRAcbqg3Y5JVECojLix3UlUQFMEvVHNSVRAIiW76LtJVEDNU+6d1kdTQJvexaqY2S9Am97FqpjZL0AcxIeX5gwlQA=="
      },
      "type": "scatter",
      "xaxis": "x",
      "yaxis": "y",
      "line": {
        "width": 0.1,
        "color": "rgb(232,119,34)"
      },
      "legendgroup": "Solar - Utility Solar",
      "marker": {
        "color": "rgb(232,119,34)"
      },
      "fillcolor": "rgb(232,119,34)"
    },
    {
      "fill": "tonexty",
      "name": "Solar - Rooftop Solar",
      "showlegend": false,
      "stackgroup": "positive",
      "x": {
        "dtype": "i4",
        "bdata": "AggAAP0HAAD4BwAA8wcAAPIHAADxBwAA8AcAAO8HAADuBwAA7QcAAOwHAADrBwAA6gcAAOkHAAA="
      },
      "y": {
        "dtype": "f8",
        "bdata": "Cf9PfTkLTkDtFNFvWvhIQMB7QJFnQkZA5j1AFNM\u002fREAKvi+EsOJDQKoPz0AHf0NA20Sbt5QSQ0AdnViuSKZCQMQnoo3lJEJARcNvyYx7QUCpopJtMJpAQNf4TPbP4z5AL0ymCka1PECPxMvTuTI6QA=="
      },
      "type": "scatter",
      "xaxis": "x",
      "yaxis": "y",
      "line": {
        "width": 0.1,
        "color": "rgb(255,184,28)"
      },
      "legendgroup": "Solar - Rooftop Solar",
      "marker": {
        "color": "rgb(255,184,28)"
      },
      "fillcolor": "rgb(255,184,28)"
    },
    {
      "fill": "tonexty",
      "name": "Turbine - Open Cycle Gas Turbine (OCGT)",
      "showlegend": false,
      "stackgroup": "positive",
      "x": {
        "dtype": "i4",
        "bdata": "AggAAP0HAAD4BwAA8wcAAPIHAADxBwAA8AcAAO8HAADuBwAA7QcAAOwHAADrBwAA6gcAAOkHAAA="
      },
      "y": {
        "dtype": "f8",
        "bdata": "9V4MqtHKAUCO+JBcFY8ZQEVZcv4NliBABuqjQ5aAIkC2vkhoy0kjQAh3Z+22myNAzXUaaakMJEDNdRppqQwkQLYtymyQOSVAti3KbJA5JUC2LcpskDklQLJGPUSjSyVAd2fttgtdJUDopPeNr40lQA=="
      },
      "type": "scatter",
      "xaxis": "x",
      "yaxis": "y",
      "line": {
        "width": 0.1,
        "color": "rgb(0,0,128)"
      },
      "legendgroup": "Turbine - Open Cycle Gas Turbine (OCGT)",
      "marker": {
        "color": "rgb(0,0,128)"
      },
      "fillcolor": "rgb(0,0,128)"
    },
    {
      "fill": "tonexty",
      "name": "Turbine - Steam - Black Coal",
      "showlegend": false,
      "stackgroup": "positive",
      "x": {
        "dtype": "i4",
        "bdata": "AggAAP0HAAD4BwAA8wcAAPIHAADxBwAA8AcAAO8HAADuBwAA7QcAAOwHAADrBwAA6gcAAOkHAAA="
      },
      "y": {
        "dtype": "f8",
        "bdata": "0FoUXtPcyD8fiezXE0TrP8mcn1U8fAVAFXiKQ\u002fx8CUASMkiBoXAPQHCvoRGF6xJANQhgcYA9F0AF4otN8lcaQHaraDbPiiBAnpLYhGDMJUDBCCI453EqQLKd76fGmzFAsp3vp8abMUCyne+nxpsxQA=="
      },
      "type": "scatter",
      "xaxis": "x",
      "yaxis": "y",
      "line": {
        "width": 0.1,
        "color": "rgb(0,0,0)"
      },
      "legendgroup": "Turbine - Steam - Black Coal",
      "marker": {
        "color": "rgb(0,0,0)"
      },
      "fillcolor": "rgb(0,0,0)"
    },
    {
      "fill": "tonexty",
      "name": "Hydro Plant",
      "showlegend": false,
      "stackgroup": "positive",
      "x": {
        "dtype": "i4",
        "bdata": "AggAAP0HAAD4BwAA8wcAAPIHAADxBwAA8AcAAO8HAADuBwAA7QcAAOwHAADrBwAA6gcAAOkHAAA="
      },
      "y": {
        "dtype": "f8",
        "bdata": "LUMc6+L2HEAtQxzr4vYcQC1DHOvi9hxAidLe4AtTHUCJ0t7gC1MdQInS3uALUx1AidLe4AtTHUCJ0t7gC1MdQInS3uALUx1AidLe4AtTHUCJ0t7gC1MdQInS3uALUx1AidLe4AtTHUAzZdH1rKIcQA=="
      },
      "type": "scatter",
      "xaxis": "x",
      "yaxis": "y",
      "line": {
        "width": 0.1,
        "color": "rgb(30,34,170)"
      },
      "legendgroup": "Hydro Plant",
      "marker": {
        "color": "rgb(30,34,170)"
      },
      "fillcolor": "rgb(30,34,170)"
    },
    {
      "fill": "tonexty",
      "name": "Turbine - Open Cycle Gas Turbine (OCGT) - Hydrogen",
      "showlegend": false,
      "stackgroup": "positive",
      "x": {
        "dtype": "i4",
        "bdata": "AggAAP0HAAD4BwAA8wcAAPIHAADxBwAA8AcAAO8HAADuBwAA7QcAAOwHAADrBwAA6gcAAOkHAAA="
      },
      "y": {
        "dtype": "f8",
        "bdata": "taDHMFCPEECsiL5xQ48QQDi6JQ45jxBA445obCyPEEAHxqEWH48QQHKfWAoYjxBAHvuFoBCPEEB6zluXC48QQHP8omkGjxBAhGdFIwGPEECEZ0UjAY8QQNWbVxPP6g1A1ZtXE8\u002fqDUBBUw3NhvEEQA=="
      },
      "type": "scatter",
      "xaxis": "x",
      "yaxis": "y",
      "line": {
        "width": 0.1,
        "color": "rgb(0,122,83)"
      },
      "legendgroup": "Turbine - Open Cycle Gas Turbine (OCGT) - Hydrogen",
      "marker": {
        "color": "rgb(0,122,83)"
      },
      "fillcolor": "rgb(0,122,83)"
    },
    {
      "fill": "tonexty",
      "name": "Turbine - Closed Cycle Gas Turbine (CCGT)",
      "showlegend": false,
      "stackgroup": "positive",
      "x": {
        "dtype": "i4",
        "bdata": "AggAAP0HAAD4BwAA8wcAAPIHAADxBwAA8AcAAO8HAADuBwAA7QcAAOwHAADrBwAA6gcAAOkHAAA="
      },
      "y": {
        "dtype": "f8",
        "bdata": "C9Cbc3eU8j9ngcukm4AGQMAQeP6YxgpAnlOt9cW3D0APnDOitLcPQA+cM6K0tw9AD5wzorS3D0APnDOitLcPQA+cM6K0tw9AD5wzorS3D0Cti9toAO8PQK2L22gA7w9ArYvbaADvD0Cti9toAO8PQA=="
      },
      "type": "scatter",
      "xaxis": "x",
      "yaxis": "y",
      "line": {
        "width": 0.1,
        "color": "rgb(117,117,121)"
      },
      "legendgroup": "Turbine - Closed Cycle Gas Turbine (CCGT)",
      "marker": {
        "color": "rgb(117,117,121)"
      },
      "fillcolor": "rgb(117,117,121)"
    },
    {
      "fill": "tonexty",
      "name": "Turbine - Steam - Brown Coal",
      "showlegend": false,
      "stackgroup": "positive",
      "x": {
        "dtype": "i4",
        "bdata": "AggAAP0HAAD4BwAA8wcAAPIHAADxBwAA8AcAAO8HAADuBwAA7QcAAOwHAADrBwAA6gcAAOkHAAA="
      },
      "y": {
        "dtype": "f8",
        "bdata": "FsQEwecA5z5EyVG7fO\u002fZP61ytXtYj+I\u002fmrx6nHtk\u002fz8VrkfhehQLQBWuR+F6FAtAFa5H4XoUC0AVrkfhehQLQBWuR+F6FAtAFa5H4XoUC0AhUtNHqkcTQEjhehSuRxNASOF6FK5HE0BI4XoUrkcTQA=="
      },
      "type": "scatter",
      "xaxis": "x",
      "yaxis": "y",
      "line": {
        "width": 0.1,
        "color": "rgb(102,51,0)"
      },
      "legendgroup": "Turbine - Steam - Brown Coal",
      "marker": {
        "color": "rgb(102,51,0)"
      },
      "fillcolor": "rgb(102,51,0)"
    },
    {
      "fill": "tonexty",
      "name": "Solar - Solar Thermal",
      "showlegend": false,
      "stackgroup": "positive",
      "x": {
        "dtype": "i4",
        "bdata": "AggAAP0HAAD4BwAA8wcAAPIHAAA="
      },
      "y": {
        "dtype": "f8",
        "bdata": "p7T5+hxXaD\u002fFXWuQGrRkP8tfEtTRIF0\u002f6Tsv8SJMSD\u002fRk+BbUukwPw=="
      },
      "type": "scatter",
      "xaxis": "x",
      "yaxis": "y",
      "line": {
        "width": 0.1,
        "color": "rgb(107,142,35)"
      },
      "legendgroup": "Solar - Solar Thermal",
      "marker": {
        "color": "rgb(107,142,35)"
      },
      "fillcolor": "rgb(107,142,35)"
    },
    {
      "fill": "tonexty",
      "name": "Engine - Reciprocating Engine",
      "showlegend": false,
      "stackgroup": "positive",
      "x": {
        "dtype": "i4",
        "bdata": "AggAAP0HAAD4BwAA8wcAAPIHAADxBwAA8AcAAO8HAADuBwAA7QcAAOwHAADrBwAA6gcAAOkHAAA="
      },
      "y": {
        "dtype": "f8",
        "bdata": "IOr7hG581z\u002f5+nE2QBTpP4rlllZD4uw\u002fiuWWVkPi7D+K5ZZWQ+LsP4rlllZD4uw\u002fiuWWVkPi7D+K5ZZWQ+LsP4rlllZD4uw\u002fiuWWVkPi7D+K5ZZWQ+LsP4rlllZD4uw\u002fiuWWVkPi7D+A\u002fuhV\u002fSDrPw=="
      },
      "type": "scatter",
      "xaxis": "x",
      "yaxis": "y",
      "line": {
        "width": 0.1,
        "color": "rgb(113,204,152)"
      },
      "legendgroup": "Engine - Reciprocating Engine",
      "marker": {
        "color": "rgb(113,204,152)"
      },
      "fillcolor": "rgb(113,204,152)"
    },
    {
      "fill": "tonexty",
      "name": "Engine - Cogeneration",
      "showlegend": false,
      "stackgroup": "positive",
      "x": {
        "dtype": "i4",
        "bdata": "AggAAP0HAAD4BwAA8wcAAPIHAADxBwAA8AcAAO8HAADuBwAA7QcAAOwHAADrBwAA6gcAAOkHAAA="
      },
      "y": {
        "dtype": "f8",
        "bdata": "I\u002fIHAsNRtD9AdPmn6s\u002fXP24Sg8DKoeE\u002fbhKDwMqh4T++nxov3STiP76fGi\u002fdJOI\u002fvp8aL90k4j++nxov3STiP5LLf0i\u002ffeM\u002fkst\u002fSL994z+Sy39Iv33jP5LLf0i\u002ffeM\u002fkst\u002fSL994z+Sy39Iv33jPw=="
      },
      "type": "scatter",
      "xaxis": "x",
      "yaxis": "y",
      "line": {
        "width": 0.1,
        "color": "rgb(67,194,204)"
      },
      "legendgroup": "Engine - Cogeneration",
      "marker": {
        "color": "rgb(67,194,204)"
      },
      "fillcolor": "rgb(67,194,204)"
    },
    {
      "fill": "tonexty",
      "name": "Turbine - Open Cycle Gas Turbine (OCGT) - Oil Distillate",
      "showlegend": false,
      "stackgroup": "positive",
      "x": {
        "dtype": "i4",
        "bdata": "8wcAAPIHAADxBwAA8AcAAO8HAADuBwAA7QcAAOwHAADrBwAA6gcAAOkHAAA="
      },
      "y": {
        "dtype": "f8",
        "bdata": "YJ9KrcY7kj+amZmZmZmpP1pkO99Pjd8\u002fWmQ730+N3z9aZDvfT43fP0w3iUFg5eQ\u002fTDeJQWDl5D9MN4lBYOXkP0w3iUFg5eQ\u002fTDeJQWDl5D9MN4lBYOXkPw=="
      },
      "type": "scatter",
      "xaxis": "x",
      "yaxis": "y",
      "line": {
        "width": 0.1,
        "color": "rgb(44,44,44)"
      },
      "legendgroup": "Turbine - Open Cycle Gas Turbine (OCGT) - Oil Distillate",
      "marker": {
        "color": "rgb(44,44,44)"
      },
      "fillcolor": "rgb(44,44,44)"
    }
  ],
  "layout": {
    "template": {
      "data": {
        "scatter": [
          {
            "line": {
              "width": 5
            },
            "opacity": 0.7,
            "type": "scatter"
          }
        ]
      },
      "layout": {
        "bargap": 0.5,
        "colorway": [
          "rgb(0,29,52)",
          "rgb(0,0,128)",
          "rgb(30,34,170)",
          "rgb(0,75,135)",
          "rgb(0,115,119)",
          "rgb(0,169,206)",
          "rgb(67,194,204)",
          "rgb(159,174,229)",
          "rgb(34,70,34)",
          "rgb(0,122,83)",
          "rgb(107,142,35)",
          "rgb(120,190,32)",
          "rgb(113,204,152)",
          "rgb(232,119,34)",
          "rgb(255,184,28)",
          "rgb(109,32,119)",
          "rgb(223,25,149)",
          "rgb(0,0,0)",
          "rgb(44,44,44)",
          "rgb(80,80,80)",
          "rgb(158,158,158)",
          "rgb(117,117,121)",
          "rgb(200,200,220)",
          "rgb(102,51,0)",
          "rgb(128,0,0)"
        ],
        "font": {
          "family": "Arial",
          "size": 15
        },
        "legend": {
          "entrywidth": 0,
          "entrywidthmode": "pixels",
          "font": {
            "size": 15
          },
          "itemsizing": "constant",
          "itemwidth": 30,
          "orientation": "h",
          "traceorder": "normal",
          "x": 0.5,
          "xanchor": "center",
          "y": -0.05,
          "yanchor": "top"
        },
        "margin": {
          "b": 105,
          "r": 25,
          "t": 50
        },
        "paper_bgcolor": "white",
        "plot_bgcolor": "white",
        "title": {
          "font": {
            "color": "#333333",
            "size": 16
          }
        },
        "xaxis": {
          "showgrid": false,
          "tickfont": {
            "size": 15
          },
          "title": {
            "font": {
              "size": 15
            }
          }
        },
        "yaxis": {
          "gridcolor": "lightgrey",
          "tickfont": {
            "size": 15
          },
          "title": {
            "font": {
              "size": 15
            }
          }
        }
      }
    },
    "xaxis": {
      "anchor": "y",
      "domain": [
        0.0,
        0.45
      ],
      "title": {
        "text": ""
      }
    },
    "yaxis": {
      "anchor": "x",
      "domain": [
        0.0,
        0.47
      ],
      "title": {
        "text": "GW"
      },
      "showticklabels": true,
      "nticks": 10,
      "matches": "y",
      "range": [
        -25.0,
        825.0
      ]
    },
    "xaxis2": {
      "anchor": "y2",
      "domain": [
        0.55,
        1.0
      ],
      "matches": "x",
      "title": {
        "text": ""
      }
    },
    "yaxis2": {
      "anchor": "x2",
      "domain": [
        0.0,
        0.47
      ],
      "matches": "y",
      "showticklabels": true,
      "nticks": 10,
      "range": [
        -25.0,
        825.0
      ],
      "title": {
        "text": "GW"
      }
    },
    "xaxis3": {
      "anchor": "y3",
      "domain": [
        0.0,
        0.45
      ],
      "matches": "x",
      "showticklabels": false,
      "title": {
        "text": ""
      }
    },
    "yaxis3": {
      "anchor": "x3",
      "domain": [
        0.53,
        1.0
      ],
      "matches": "y",
      "title": {
        "text": "GW"
      },
      "showticklabels": true,
      "nticks": 10,
      "range": [
        -25.0,
        825.0
      ]
    },
    "xaxis4": {
      "anchor": "y4",
      "domain": [
        0.55,
        1.0
      ],
      "matches": "x",
      "showticklabels": false,
      "title": {
        "text": ""
      }
    },
    "yaxis4": {
      "anchor": "x4",
      "domain": [
        0.53,
        1.0
      ],
      "matches": "y",
      "showticklabels": true,
      "nticks": 10,
      "range": [
        -25.0,
        825.0
      ],
      "title": {
        "text": "GW"
      }
    },
    "annotations": [
      {
        "font": {
          "color": "black",
          "family": "Arial",
          "size": 15
        },
        "showarrow": false,
        "text": "\u003cb\u003eAmpol-House-View\u003c\u002fb\u003e\u003cbr\u003eElectricity Generation Capacity by Tech and Fuel",
        "x": 0.225,
        "xanchor": "center",
        "xref": "paper",
        "y": 0.48,
        "yanchor": "bottom",
        "yref": "paper"
      },
      {
        "font": {
          "color": "black",
          "family": "Arial",
          "size": 15
        },
        "showarrow": false,
        "text": "\u003cb\u003eAmpol-1p5DS\u003c\u002fb\u003e\u003cbr\u003eElectricity Generation Capacity by Tech and Fuel",
        "x": 0.225,
        "xanchor": "center",
        "xref": "paper",
        "y": 1.01,
        "yanchor": "bottom",
        "yref": "paper"
      },
      {
        "font": {
          "color": "black",
          "family": "Arial",
          "size": 15
        },
        "showarrow": false,
        "text": "\u003cb\u003eAmpol-2p5DS\u003c\u002fb\u003e\u003cbr\u003eElectricity Generation Capacity by Tech and Fuel",
        "x": 0.775,
        "xanchor": "center",
        "xref": "paper",
        "y": 1.01,
        "yanchor": "bottom",
        "yref": "paper"
      },
      {
        "font": {
          "color": "darkgrey",
          "size": 8
        },
        "showarrow": false,
        "text": "2025-12-03 Copyright © CSIRO",
        "x": 1,
        "xanchor": "right",
        "xref": "paper",
        "y": -0.05,
        "yanchor": "top",
        "yref": "paper"
      }
    ],
    "legend": {
      "tracegroupgap": 0,
      "title": {
        "text": ""
      },
      "y": -0.07,
      "yanchor": "top",
      "xanchor": "center",
      "x": 0.5
    },
    "title": {
      "text": ""
    },
    "shapes": [
      {
        "line": {
          "color": "black",
          "width": 1
        },
        "type": "line",
        "x0": 0,
        "x1": 1,
        "xref": "x domain",
        "y0": 0,
        "y1": 0,
        "yref": "y"
      },
      {
        "line": {
          "color": "black",
          "width": 1
        },
        "type": "line",
        "x0": 0,
        "x1": 1,
        "xref": "x3 domain",
        "y0": 0,
        "y1": 0,
        "yref": "y3"
      },
      {
        "line": {
          "color": "black",
          "width": 1
        },
        "type": "line",
        "x0": 0,
        "x1": 1,
        "xref": "x4 domain",
        "y0": 0,
        "y1": 0,
        "yref": "y4"
      }
    ],
    "modebar": {
      "add": [
        "v1hovermode",
        "toggleSpikelines",
        "drawline",
        "hoverClosestGl2d",
        "drawopenpath",
        "drawclosedpath",
        "drawcircle",
        "drawrect",
        "eraseshape"
      ]
    }
  }
}